{
 "loop": 2,
 "panel": [
  {
   "lens": "reviewer",
   "verdicts": [
    {
     "image": "img_01.png",
     "call": "CG_RENDER",
     "confidence": 95,
     "tells": [
      "Two objects sit on a perfectly uniform gradient-lit black plane with no dust, seams or real-world surface texture",
      "The gold foam-metal block shows procedurally repeating pore noise and unnaturally clean beveled edges typical of a 3D material shader",
      "Soft, physically idealized contact shadows and blur falloff read as path-traced GI, not a camera lens"
     ]
    },
    {
     "image": "img_02.png",
     "call": "PHOTOGRAPH",
     "confidence": 72,
     "tells": [
      "Soft diffuse studio softbox gradient on a seamless sweep with a believable faint floor reflection",
      "Bead-blasted anodized metal shows subtle real grain and slightly uneven tone across the face",
      "Minor real-world imperfections: gentle vignetting and a soft undercut shadow consistent with a product light tent"
     ]
    },
    {
     "image": "img_03.png",
     "call": "CG_RENDER",
     "confidence": 96,
     "tells": [
      "Top surface antenna/sensor dots are blurred and float under the metal in a way real anodized aluminum never shows",
      "Edges have an idealized uniform highlight rim and the material lacks any micro-scratches or fingerprints",
      "Background is a pure synthetic dark gradient with a too-perfect chamfer specular line"
     ]
    },
    {
     "image": "img_04.png",
     "call": "PHOTOGRAPH",
     "confidence": 90,
     "tells": [
      "Complex real scene: window daylight, foliage bokeh, cluttered studio gear and a person with natural skin and hair detail",
      "Screens show believable moire, pixel glow and off-axis reflections consistent with a real camera capture",
      "Depth of field, mixed color temperature and lens falloff are photographic, not uniformly rendered"
     ]
    },
    {
     "image": "img_05.png",
     "call": "CG_RENDER",
     "confidence": 93,
     "tells": [
      "Aluminum body is flawless with a plasticky even specular sheen and no surface texture or dust",
      "Bottom mesh grille is a suspiciously regular pattern and the reflection on the floor is idealized",
      "Lighting is a single soft synthetic key on a pure gradient backdrop with no environment reflections"
     ]
    },
    {
     "image": "img_06.png",
     "call": "PHOTOGRAPH",
     "confidence": 68,
     "tells": [
      "Open-cell foam metal shows genuinely stochastic, non-repeating pore structure with real depth and occlusion",
      "The dark blue port interior has a plausible real specular reflection and slightly soft focus falloff",
      "Even studio sweep with faint gradient and micro-noise consistent with a real sensor at moderate ISO"
     ]
    },
    {
     "image": "img_07.png",
     "call": "PHOTOGRAPH",
     "confidence": 82,
     "tells": [
      "Very clean product-studio lighting on a seamless white with soft even shadow and gentle reflection under the chassis",
      "Metal shows subtle real anodized grain and a faint tone gradient rather than a flat synthetic fill",
      "The port cutout and status LED render with photographic edge softness and no idealized shader highlights"
     ]
    },
    {
     "image": "img_08.png",
     "call": "CG_RENDER",
     "confidence": 88,
     "tells": [
      "Extreme macro of the foam metal shows pore geometry that looks tessellated/procedural rather than organically random",
      "The gold bezel around the port is unnaturally smooth and clean with a uniform shader-like sheen",
      "Depth of field and background blur are too smoothly synthetic, lacking real lens aberration or grain"
     ]
    },
    {
     "image": "img_09.png",
     "call": "PHOTOGRAPH",
     "confidence": 91,
     "tells": [
      "Real Apple laser-etched logo, believable brushed-aluminum micro grain and faint handling marks on the top surface",
      "Uneven, slightly warm studio lighting with a genuine soft floor shadow and subtle sensor noise in the white sweep",
      "Port slot and chamfer edges have authentic photographic softness and specular variation"
     ]
    },
    {
     "image": "img_10.png",
     "call": "CG_RENDER",
     "confidence": 96,
     "tells": [
      "Foam-metal pores form an obviously repeating procedural tile with uniform highlight speckle across the whole face",
      "Body sits on a featureless dark gradient plane with an idealized soft contact shadow and no real environment",
      "Bezels and top slot vent are perfectly clean CAD-smooth surfaces with shader-uniform gold coloring"
     ]
    },
    {
     "image": "img_11.png",
     "call": "PHOTOGRAPH",
     "confidence": 94,
     "tells": [
      "Real StorageReview lab backdrop with rack gear, out-of-focus green/blue status LEDs rendering as true bokeh discs",
      "Scratched wooden workbench with genuine wear marks and a natural mixed-lighting color cast",
      "Shallow DOF, sensor grain and authentic specular play across the foam metal all read photographic"
     ]
    },
    {
     "image": "img_12.png",
     "call": "CG_RENDER",
     "confidence": 94,
     "tells": [
      "Foam texture and gold bevels are pristine and CAD-smooth with a shader-even sheen and no real defects",
      "Top face has a perfectly regular diagonal brushed pattern and a too-clean recessed panel outline",
      "Object floats on a pure dark gradient with idealized soft GI shadow and no environmental reflections"
     ]
    },
    {
     "image": "img_13.png",
     "call": "PHOTOGRAPH",
     "confidence": 80,
     "tells": [
      "Classic two-tone studio product shot (blue backdrop, white acrylic base) with a realistic mirror reflection below",
      "Polished gold handle shows a genuine environment reflection including the blurred backdrop and soft box",
      "Foam-metal pores are organically random with real specular glints and subtle focus falloff toward the edges"
     ]
    }
   ]
  },
  {
   "lens": "lookdev",
   "verdicts": [
    {
     "image": "img_01.png",
     "call": "CG_RENDER",
     "confidence": 88,
     "tells": [
      "Both objects sit on an ideal dark plane with soft, uniform CG contact shadows and no real surface grain",
      "Silver metal is a flat matte 'clay' shader with no micro-scratches, dust or fingerprints",
      "Gold foam reads as procedural bump/displacement, and the clean-product-plus-exotic-material pairing is a classic lookdev turntable setup"
     ]
    },
    {
     "image": "img_02.png",
     "call": "PHOTOGRAPH",
     "confidence": 72,
     "tells": [
      "Natural seamless-backdrop falloff with a realistic soft, slightly asymmetric contact shadow",
      "Anodized surface carries subtle believable noise and gradient rather than a clean shader sweep",
      "Faint real sensor characteristics and even studio softbox lighting consistent with a product photo"
     ]
    },
    {
     "image": "img_03.png",
     "call": "CG_RENDER",
     "confidence": 90,
     "tells": [
      "Rim/edge highlight is a perfectly even razor-thin CG bevel line with no roughness variation",
      "Brushed metal is spotless with zero dust, fingerprints or scuffs and an unrealistically clean surface",
      "Background and floor are a pure procedural dark gradient with no environmental detail"
     ]
    },
    {
     "image": "img_04.png",
     "call": "PHOTOGRAPH",
     "confidence": 95,
     "tells": [
      "Real human subject with convincing skin, hair, stubble and glasses",
      "Natural depth of field, window daylight bounce and believable on-screen DAW content",
      "Complex cluttered studio environment with authentic material variety and reflections"
     ]
    },
    {
     "image": "img_05.png",
     "call": "CG_RENDER",
     "confidence": 85,
     "tells": [
      "Body gradient is too smooth and evenly falls off like a shader rather than real anodized aluminum",
      "Bottom speaker mesh looks modeled/tiled rather than a real perforated grille",
      "Sweep background and surface are immaculately clean with CG-perfect edge highlights"
     ]
    },
    {
     "image": "img_06.png",
     "call": "PHOTOGRAPH",
     "confidence": 70,
     "tells": [
      "Realistic studio seamless sweep with natural soft gradient and grounded shadow",
      "Metal end caps show believable real reflections and a plausible printed NVIDIA logo",
      "Subtle sensor grain and slightly irregular foam pore variation consistent with a real object"
     ]
    },
    {
     "image": "img_07.png",
     "call": "PHOTOGRAPH",
     "confidence": 80,
     "tells": [
      "Real anodized aluminum with authentic subtle surface texture and machined bevel",
      "Genuine perforated speaker mesh at the base with real depth",
      "Clean Apple press-style lighting on a true seamless white with natural soft shadow"
     ]
    },
    {
     "image": "img_08.png",
     "call": "CG_RENDER",
     "confidence": 90,
     "tells": [
      "Metal-foam cells are unnaturally uniform in scale and distribution, reading as procedural noise/displacement",
      "Port opening is a flat plastic-looking recess with a too-clean rounded bevel",
      "Overall bump/normal detail is even across the whole face with no real focus falloff or dust"
     ]
    },
    {
     "image": "img_09.png",
     "call": "PHOTOGRAPH",
     "confidence": 88,
     "tells": [
      "Real machined aluminum with fine authentic surface micro-texture and etched Apple logo",
      "Natural soft studio shadow and realistic top-surface reflection gradient",
      "Believable material contrast between matte top and brushed body typical of a real product shot"
     ]
    },
    {
     "image": "img_10.png",
     "call": "CG_RENDER",
     "confidence": 90,
     "tells": [
      "Foam texture is procedural with overly even cell size and repetitive bump pattern",
      "Gold surfaces have a plasticky, clay-like sheen with perfectly rounded CG bevels",
      "Studio floor and contact shadow are a clean synthetic gradient with no real-world imperfections"
     ]
    },
    {
     "image": "img_11.png",
     "call": "PHOTOGRAPH",
     "confidence": 85,
     "tells": [
      "Real out-of-focus LED bokeh and blurred lab rack background with authentic falloff",
      "Wood bench shows genuine grain and scratches with natural lighting",
      "Believable shallow depth of field and real reflections on the metal handles"
     ]
    },
    {
     "image": "img_12.png",
     "call": "CG_RENDER",
     "confidence": 91,
     "tells": [
      "Foam surface is clearly procedural with uniform pore scale and even displacement",
      "Gold material looks plasticky with idealized rounded edges and modeled top vent slot",
      "Lighting and dark floor are a clean CG studio setup lacking real environmental cues"
     ]
    },
    {
     "image": "img_13.png",
     "call": "PHOTOGRAPH",
     "confidence": 72,
     "tells": [
      "Real acrylic tabletop reflection of the unit and a genuine colored-paper backdrop",
      "Polished metal handles show authentic specular reflections and a real printed NVIDIA logo",
      "Natural irregular foam pore variation and subtle photographic grain"
     ]
    }
   ]
  },
  {
   "lens": "photographer",
   "verdicts": [
    {
     "image": "img_01.png",
     "call": "CG_RENDER",
     "confidence": 92,
     "tells": [
      "Two disparate objects share one perfectly uniform gradient backdrop with no seam, floor-to-wall transition, or real light falloff",
      "The gold foam-metal texture reads as a procedural/tiled displacement map, too even in cell size and specular response for a real sintered surface",
      "Ground shadows are clean ray-traced contact shadows with no dust, micro-scratches, or real-world floor imperfections"
     ]
    },
    {
     "image": "img_02.png",
     "call": "PHOTOGRAPH",
     "confidence": 74,
     "tells": [
      "Soft real seamless-sweep falloff with a genuine soft shadow pooling under the chassis and a faint floor reflection",
      "Anodized-metal microtexture shows real sensor grain and subtle tonal blotching consistent with bead-blasted aluminum",
      "Slightly imperfect edge highlight and a real out-of-focus foreground/background gradient typical of a studio softbox setup"
     ]
    },
    {
     "image": "img_03.png",
     "call": "CG_RENDER",
     "confidence": 90,
     "tells": [
      "The internal antenna/dot pattern bleeding through the top surface is a raytraced subsurface artifact, not how real anodized aluminum behaves",
      "Edge highlights are too clean and mathematically continuous around the fillet; no anisotropic brush streaks or real dust",
      "Backdrop and contact shadow are a flawless synthetic gradient with no floor texture or environmental reflection"
     ]
    },
    {
     "image": "img_04.png",
     "call": "PHOTOGRAPH",
     "confidence": 88,
     "tells": [
      "Rich real-scene complexity: window daylight, monitor moire/pixel glow, cluttered gear with authentic depth-of-field falloff",
      "Skin texture, hair flyaways, and fabric weave on the subject show true lens rendering and sensor noise",
      "Multiple mixed light sources (window, RECORDING sign, screens) cast physically consistent overlapping shadows"
     ]
    },
    {
     "image": "img_05.png",
     "call": "CG_RENDER",
     "confidence": 87,
     "tells": [
      "Surface is unnaturally spotless with a perfectly smooth gradient falloff across the aluminum face; no micro-scratches or dust",
      "Bottom mesh/grille band looks like a low-detail procedural strip rather than photographed perforations",
      "Dramatic single-key lighting with pristine ray-traced contact shadow and no environmental reflections on the metal"
     ]
    },
    {
     "image": "img_06.png",
     "call": "PHOTOGRAPH",
     "confidence": 80,
     "tells": [
      "Real seamless-sweep studio backdrop with authentic soft gradient and gentle floor reflection",
      "The blue anodized recessed metal shows a genuine specular smear reflecting the softbox with real-world unevenness",
      "Foam-metal grille has irregular, non-repeating cell structure with true depth and self-shadowing consistent with a real sintered part"
     ]
    },
    {
     "image": "img_07.png",
     "call": "PHOTOGRAPH",
     "confidence": 62,
     "tells": [
      "Macro depth-of-field falloff is optically believable, sharpening toward the near port and blurring the far end",
      "The rounded port bezel shows a real soft specular gradient from a diffuse studio source",
      "Foam-metal cells are irregular and non-tiled with plausible self-cast micro-shadowing, though the smooth backdrop raises some doubt"
     ]
    },
    {
     "image": "img_08.png",
     "call": "PHOTOGRAPH",
     "confidence": 90,
     "tells": [
      "Textbook product shot on a real light sweep with soft graded shadow and authentic aluminum bead-blast microtexture",
      "The etched Apple logo shows a true directional sheen change against the brushed top, exactly as real anodized metal reflects",
      "Subtle real dust specks and tonal variation across the top surface with correct sensor grain in shadow areas"
     ]
    },
    {
     "image": "img_09.png",
     "call": "CG_RENDER",
     "confidence": 93,
     "tells": [
      "The foam-metal texture is an obvious procedural displacement pattern with repetitive bumps and uniform bright specular dots",
      "Gold body highlight rolls off with the flat matte-shader look of a render, lacking real metallic anisotropy",
      "Dark studio backdrop and shadow are a flawless synthetic gradient with no floor grain or ambient reflection"
     ]
    },
    {
     "image": "img_10.png",
     "call": "PHOTOGRAPH",
     "confidence": 85,
     "tells": [
      "Rich real environment: bokeh'd StorageReview backdrop with defocused LED status lights forming true circular bokeh discs",
      "Authentic wooden bench with real scratches, and consistent optical depth-of-field between subject and background",
      "The polished gold NVIDIA handle plate shows a genuine complex reflection of the room, not a clean CG highlight"
     ]
    },
    {
     "image": "img_11.png",
     "call": "CG_RENDER",
     "confidence": 94,
     "tells": [
      "The foam texture is a clearly repeating procedural bump map with uniform cell size and specular response across the whole face",
      "Top surface has an idealized anisotropic-line pattern that is too regular and clean for a real machined lid",
      "Perfectly gradient dark backdrop with a synthetic contact shadow and no dust, fingerprints, or floor detail"
     ]
    },
    {
     "image": "img_12.png",
     "call": "PHOTOGRAPH",
     "confidence": 55,
     "tells": [
      "Foam-metal cells appear irregular and non-repeating with plausible depth and self-shadowing of a real sintered surface",
      "Blue seamless-sweep backdrop with a genuine glossy tabletop reflection of the unit below",
      "Gold handle plates show real, uneven specular smears reflecting the studio environment rather than clean CG highlights"
     ]
    },
    {
     "image": "img_13.png",
     "call": "PHOTOGRAPH",
     "confidence": 60,
     "tells": [
      "Same unit as img_12 on a blue sweep with a convincing glossy-floor mirror reflection including the inverted NVIDIA logo",
      "The right handle plate carries a complex real-room reflection (dark shapes, gradient) rather than a synthetic gloss",
      "Foam-metal structure has irregular natural cell variation and true micro depth typical of a photographed sintered part"
     ]
    }
   ]
  },
  {
   "lens": "materials",
   "verdicts": [
    {
     "image": "img_01.png",
     "call": "CG_RENDER",
     "confidence": 96,
     "tells": [
      "The gold unit's foam-metal texture is a tiling procedural bump/displacement pattern with uniform cell size and no real subsurface depth \u2014 reads as a shader, not physical open-cell foam",
      "Both objects sit on a perfectly clean gradient floor with idealized soft shadows and zero dust, fingerprints or micro-scratches",
      "The silver box's top-surface dimples are blurred symmetric artifacts with no plausible physical cause, typical of a displaced/subdivided mesh"
     ]
    },
    {
     "image": "img_02.png",
     "call": "PHOTOGRAPH",
     "confidence": 80,
     "tells": [
      "Bead-blasted anodized aluminium reads correctly: even micro-speckle sheen with a soft real specular falloff across the face",
      "Grounded contact shadow and faint tabletop reflection consistent with a real softbox studio shot on seamless paper",
      "Slightly imperfect, asymmetric lighting gradient and subtle sensor noise rather than clean render-perfect falloff"
     ]
    },
    {
     "image": "img_03.png",
     "call": "CG_RENDER",
     "confidence": 94,
     "tells": [
      "Extremely narrow, physically inconsistent depth-of-field with dreamy blurred dimples on the top that no real macro lens/subject would produce this way",
      "Edge highlight is a razor-thin idealized specular line with no anodizing grain, and surface has zero dust or handling marks",
      "Backlit dark studio with a perfectly smooth radial falloff \u2014 classic single-HDRI/area-light render setup"
     ]
    },
    {
     "image": "img_04.png",
     "call": "PHOTOGRAPH",
     "confidence": 90,
     "tells": [
      "Real environmental complexity: window foliage, studio monitors, cables, reflections and screen glare all lit consistently by one soft daylight source",
      "Natural skin, hair and fabric detail on the person with authentic motion-plausible hand position on the keyboard",
      "Mac Studio has believable anodized sheen with real reflections of the desk clutter \u2014 no render-clean surface"
     ]
    },
    {
     "image": "img_05.png",
     "call": "CG_RENDER",
     "confidence": 90,
     "tells": [
      "Surface is a flawless matte aluminium with a mathematically smooth luminance gradient and no bead-blast micro-grain visible at this scale",
      "Perimeter mesh/foot band is a low-detail suggestion rather than a real perforated grille, and edges are perfectly uniform fillets",
      "Dark seamless studio with a single clean soft shadow and reflection, no dust or fingerprints anywhere"
     ]
    },
    {
     "image": "img_06.png",
     "call": "PHOTOGRAPH",
     "confidence": 78,
     "tells": [
      "Open-cell metal foam shows real irregular pore depth with genuine occlusion and stray broken ligaments at the edges \u2014 hard to fake convincingly",
      "Anodized gold end caps show real brushed/machined streaks and a plausible dark reflective port with a printed NVIDIA logo",
      "Soft studio gradient background with a natural grounded shadow and mild sensor grain"
     ]
    },
    {
     "image": "img_07.png",
     "call": "PHOTOGRAPH",
     "confidence": 88,
     "tells": [
      "Perfect seamless white infinity-cove lighting with even wraparound and a soft grounded shadow typical of Apple product studio photography",
      "Bead-blasted anodized aluminium reads authentically with a smooth realistic specular gradient and correctly rendered speaker grille perforations",
      "Subtle real reflections and micro tonal variation on the face rather than a synthetic uniform sheen"
     ]
    },
    {
     "image": "img_08.png",
     "call": "CG_RENDER",
     "confidence": 95,
     "tells": [
      "Macro of the foam shows a cracked-cell procedural texture with repeating cell geometry and flat lighting \u2014 no true pore depth or shadow occlusion",
      "The top-surface fine diagonal line pattern is an aliased procedural stripe with no physical machining logic",
      "Bevel edges and the port cutout are perfectly uniform CAD fillets with unnaturally clean paint over a rough substrate"
     ]
    },
    {
     "image": "img_09.png",
     "call": "PHOTOGRAPH",
     "confidence": 82,
     "tells": [
      "Real reflective anodized top surface with a genuine slightly-off specular of the environment and true Apple logo etch",
      "Bead-blasted casing has authentic micro-texture and natural subtle unevenness in the studio lighting",
      "Soft plausible contact shadow on off-white seamless with faint imperfections consistent with a real photo"
     ]
    },
    {
     "image": "img_10.png",
     "call": "CG_RENDER",
     "confidence": 93,
     "tells": [
      "Foam texture is a bumpy pebbled displacement without real open-cell voids or deep occlusion, uniform across the whole face",
      "Perfectly smooth gold end caps and idealized fillets with a single clean warm key light and soft reflection floor",
      "Dark seamless studio, zero dust or handling wear, and blurred port interiors that lack real geometric depth"
     ]
    },
    {
     "image": "img_11.png",
     "call": "PHOTOGRAPH",
     "confidence": 85,
     "tells": [
      "Real depth-of-field bokeh on background rack with defocused green/blue status LEDs and a legible StorageReview banner",
      "Genuine wooden workbench with fine scratches and grain, lit consistently with the foreground unit",
      "Open-cell metal foam shows authentic pore depth and real occlusion, with polished gold handles reflecting the room correctly"
     ]
    },
    {
     "image": "img_12.png",
     "call": "CG_RENDER",
     "confidence": 95,
     "tells": [
      "Identical to img_08 framing: cracked procedural foam texture with repeating cell pattern and no real pore depth or occlusion",
      "Top face diagonal micro-lines are an aliased procedural pattern, and all edges are flawless CAD fillets",
      "Studio-clean lighting on a dark seamless with unnaturally perfect paint over a rough foam substrate"
     ]
    },
    {
     "image": "img_13.png",
     "call": "PHOTOGRAPH",
     "confidence": 76,
     "tells": [
      "Open-cell foam shows real irregular pore geometry with genuine depth and occlusion, plus polished gold handles giving true mirror reflections",
      "Clean studio blue-backdrop shot with a realistic glossy tabletop reflection of the unit including the mirrored logo",
      "Handle polish shows real environment reflections and subtle smudging rather than a synthetic uniform gloss"
     ]
    }
   ]
  },
  {
   "lens": "buyer",
   "verdicts": [
    {
     "image": "img_01.png",
     "call": "CG_RENDER",
     "confidence": 95,
     "tells": [
      "Both objects share an identical, unnaturally smooth studio gradient floor with a flawless perfect-black background falloff typical of 3D renders",
      "The silver unit's surface is too perfectly clean with soft ghost-like circular shadows bleeding through the top that look like unresolved subsurface/AO artifacts, not real reflections",
      "The gold foam texture is uniform and procedurally repetitive with edges that are too crisp against the smooth metal rim - reads as a displacement material, not physical foam metal"
     ]
    },
    {
     "image": "img_02.png",
     "call": "PHOTOGRAPH",
     "confidence": 72,
     "tells": [
      "Even softbox studio lighting with a natural graduated backdrop and a realistic soft floor reflection under the unit",
      "Subtle real-world imperfections: slightly uneven bottom shadow gap and a faint sensor-like grain across the flat panel",
      "Matte anodized aluminum finish shows the slightly blotchy, non-uniform sheen you get from a real bead-blasted surface under diffuse light"
     ]
    },
    {
     "image": "img_03.png",
     "call": "CG_RENDER",
     "confidence": 94,
     "tells": [
      "Ghostly soft circular blobs floating under the top surface (internal component shadows) that no real anodized aluminum lid would show",
      "Edges and chamfers are mathematically perfect with an idealized specular highlight running the whole rim like a rendered bevel",
      "The dark ground plane has a synthetic gradient and lacks any real dust, scratches, or environmental reflection"
     ]
    },
    {
     "image": "img_04.png",
     "call": "PHOTOGRAPH",
     "confidence": 90,
     "tells": [
      "Complex real-world environment: window daylight, foliage, cluttered studio gear, a person with natural skin and hair detail",
      "Screens show authentic UI with moire and off-axis viewing angle, and realistic reflections/glare on the displays",
      "Natural depth-of-field falloff and mixed color temperature (warm desk lamp vs cool window) consistent with a real camera"
     ]
    },
    {
     "image": "img_05.png",
     "call": "CG_RENDER",
     "confidence": 90,
     "tells": [
      "The aluminum is uncannily blemish-free with a soft airbrushed gradient and no micro-scratches or real reflections of a room",
      "The bottom mesh/foot band and port cutouts are crisp and idealized against a synthetic dark gradient floor",
      "Lighting is a generic single soft key with a too-perfect falloff to pure black, characteristic of a product render scene"
     ]
    },
    {
     "image": "img_06.png",
     "call": "PHOTOGRAPH",
     "confidence": 80,
     "tells": [
      "Real seamless-paper studio sweep with a natural soft gradient and believable diffuse shadow at the base",
      "The porous metal foam shows genuine irregular, non-repeating cell structure with real depth and micro-shadowing",
      "Authentic reflection of the environment in the dark polished port window and a crisp legible NVIDIA logo etched on the metal plate"
     ]
    },
    {
     "image": "img_07.png",
     "call": "PHOTOGRAPH",
     "confidence": 85,
     "tells": [
      "Classic Apple product-shot lighting on a pure white sweep with a natural soft under-shadow",
      "The bottom mesh grille shows a real fine perforated pattern with correct perspective and subtle moire",
      "Slightly soft, believable specular gradient across the curved aluminum top consistent with a real softbox reflection"
     ]
    },
    {
     "image": "img_08.png",
     "call": "CG_RENDER",
     "confidence": 88,
     "tells": [
      "Extreme macro of the foam metal but the cell pattern looks procedurally generated and evenly tiled with unnaturally uniform lighting",
      "The rounded port bezel is glassy-perfect with no manufacturing marks and a suspiciously clean gradient interior",
      "Background is a smooth featureless dark plane with no real workbench texture or environmental cues at this magnification"
     ]
    },
    {
     "image": "img_09.png",
     "call": "PHOTOGRAPH",
     "confidence": 75,
     "tells": [
      "Bright white studio sweep with a natural soft drop shadow and realistic slightly-uneven base gap",
      "Real anodized aluminum shows subtle tonal variation and a genuine laser-etched Apple logo with correct diffuse reflectivity",
      "Minor real-world asymmetry in the port spacing and a faint dust speck near the front, consistent with a hands-on review photo"
     ]
    },
    {
     "image": "img_10.png",
     "call": "CG_RENDER",
     "confidence": 92,
     "tells": [
      "The gold foam metal texture is regular and bubbly like a procedural noise displacement, not real irregular open-cell foam",
      "Perfectly smooth dark gradient floor and pure-black backdrop with an idealized soft contact shadow",
      "Beveled edges and port frames are flawlessly uniform with a plasticky gold sheen lacking real metal micro-reflections"
     ]
    },
    {
     "image": "img_11.png",
     "call": "PHOTOGRAPH",
     "confidence": 92,
     "tells": [
      "Authentic lab environment: blurred server rack with real bokeh LED lights and a legible StorageReview logo backdrop",
      "The wooden workbench shows genuine scratches, grain, and swirl marks around the unit",
      "Real shallow depth of field with the foam metal in sharp focus and natural falloff, plus a true-to-life NVIDIA badge"
     ]
    },
    {
     "image": "img_12.png",
     "call": "CG_RENDER",
     "confidence": 90,
     "tells": [
      "The gold foam cell texture is too uniform and repetitive across the whole face, reading as a tiled procedural material",
      "Studio floor and backdrop are a flawless synthetic gradient with an idealized soft shadow and no environmental reflections",
      "The metal port frames and top edge are glassy and mathematically perfect with an artificial airbrushed gold sheen"
     ]
    },
    {
     "image": "img_13.png",
     "call": "PHOTOGRAPH",
     "confidence": 70,
     "tells": [
      "Real glossy tabletop producing a believable mirror reflection of the unit with correct perspective and slight blur",
      "Genuine open-cell metal foam with irregular non-repeating pores and real specular glints inside the cavities",
      "Polished gold handle plates show authentic smudges and environmental reflections, and the blue backdrop has a natural lighting gradient"
     ]
    }
   ]
  }
 ]
}